
[{
	"name": "Inigo Montoya",
	"address": "555 Youkilledmyfather Street",
	"company": "CodeWithChris",
	"years_of_experience": 35
},
{
	"name": "Edna Mode",
	"address": "123 Nocape Lane",
	"company": "CodeWithChris",
	"years_of_experience": 177
},
{
	"name": "Travis Bickle",
	"address": "99 Youtalkingtome Road",
	"company": "CodeWithChris",
	"years_of_experience": 99
},
{
	"name": "Walter Sobchak",
	"address": "8 Dude Place",
	"company": "CodeWithChris",
	"years_of_experience": 23
},
{
	"name": "Julius Winnfield",
	"address": "25 Ezekiel Ave",
	"company": "CodeWithChris",
	"years_of_experience": 17
}]
